scpviz/TrackedDataFrame.py
scpviz/__init__.py
scpviz/enrichment.py
scpviz/plotting.py
scpviz/setup.py
scpviz/utils.py
scpviz/pAnnData/__init__.py
scpviz/pAnnData/analysis.py
scpviz/pAnnData/base.py
scpviz/pAnnData/editing.py
scpviz/pAnnData/enrichment.py
scpviz/pAnnData/filtering.py
scpviz/pAnnData/history.py
scpviz/pAnnData/identifier.py
scpviz/pAnnData/io.py
scpviz/pAnnData/metrics.py
scpviz/pAnnData/pAnnData.py
scpviz/pAnnData/plot.py
scpviz/pAnnData/summary.py
scpviz/pAnnData/validation.py
scpviz-0.5.2a0.dist-info/LICENSE
scpviz-0.5.2a0.dist-info/METADATA
scpviz-0.5.2a0.dist-info/WHEEL
scpviz-0.5.2a0.dist-info/top_level.txt
scpviz-0.5.2a0.dist-info/RECORD
