Metadata-Version: 2.1
Name: scpviz
Version: 0.5.2a0
Summary: A package to visualize single cell proteomics (and more to come!) data
Author-email: Marion Pang <sr_pang@hotmail.com>
Project-URL: Homepage, https://github.com/gnaprs/scpviz
Project-URL: Issues, https://github.com/gnaprs/scpviz/issues
Classifier: Programming Language :: Python :: 3
Classifier: License :: OSI Approved :: MIT License
Classifier: Development Status :: 3 - Alpha
Classifier: Operating System :: OS Independent
Requires-Python: >=3.8
License-File: LICENSE
Requires-Dist: numpy
Requires-Dist: pandas
Requires-Dist: matplotlib
Requires-Dist: seaborn
Requires-Dist: upsetplot
Requires-Dist: scikit-learn
Requires-Dist: scipy
Requires-Dist: umap-learn
Requires-Dist: adjustText
Requires-Dist: anndata
Requires-Dist: requests
Requires-Dist: matplotlib-venn
Requires-Dist: pyarrow
Requires-Dist: scanpy
Requires-Dist: IPython
Requires-Dist: igraph
Requires-Dist: harmonypy
Requires-Dist: leidenalg
Requires-Dist: scikit-misc
Requires-Dist: directlfq
Provides-Extra: dev
Requires-Dist: pytest ; extra == 'dev'
Requires-Dist: coverage ; extra == 'dev'
Requires-Dist: flake8 ; extra == 'dev'
Requires-Dist: openpyxl ; extra == 'dev'
Requires-Dist: pytest-cov ; extra == 'dev'
